fastapi_basic/__init__.py
fastapi_basic/base_config.py
fastapi_basic/base_factory.py
fastapi_basic/const.py
fastapi_basic/utils.py
fastapi_basic/database/__init__.py
fastapi_basic/database/mongodb.py
fastapi_basic/exception/__init__.py
fastapi_basic/exception/base_exception.py
fastapi_basic/ext/__init__.py
fastapi_basic/ext/aws/__init__.py
fastapi_basic/ext/aws/const.py
fastapi_basic/ext/line/__init__.py
fastapi_basic/ext/line/exception.py
fastapi_basic-0.1.11.dist-info/METADATA
fastapi_basic-0.1.11.dist-info/WHEEL
fastapi_basic-0.1.11.dist-info/top_level.txt
fastapi_basic-0.1.11.dist-info/RECORD
