Metadata-Version: 2.4
Name: fastapi_basic
Version: 0.1.11
Summary: A short description of your module
Home-page: https://github.com/szx21023/fastapi-base
Author: szx21023
Author-email: szx21023@gmail.com
Classifier: Programming Language :: Python :: 3
Classifier: License :: OSI Approved :: MIT License
Classifier: Operating System :: OS Independent
Requires-Python: >=3.6
Requires-Dist: aenum==3.1.16
Requires-Dist: aiohappyeyeballs==2.6.1
Requires-Dist: aiohttp==3.10.5
Requires-Dist: aiosignal==1.3.2
Requires-Dist: amqp==5.3.1
Requires-Dist: annotated-types==0.7.0
Requires-Dist: anyio==4.9.0
Requires-Dist: attrs==25.3.0
Requires-Dist: beanie==1.29.0
Requires-Dist: billiard==4.2.1
Requires-Dist: boto3==1.37.36
Requires-Dist: botocore==1.37.36
Requires-Dist: celery==5.5.2
Requires-Dist: certifi==2025.1.31
Requires-Dist: charset-normalizer==3.4.1
Requires-Dist: click==8.1.8
Requires-Dist: click-didyoumean==0.3.1
Requires-Dist: click-plugins==1.1.1
Requires-Dist: click-repl==0.3.0
Requires-Dist: Deprecated==1.2.18
Requires-Dist: dnspython==2.7.0
Requires-Dist: dotenv==0.9.9
Requires-Dist: fastapi==0.115.12
Requires-Dist: frozenlist==1.6.0
Requires-Dist: future==1.0.0
Requires-Dist: h11==0.16.0
Requires-Dist: idna==3.10
Requires-Dist: jmespath==1.0.1
Requires-Dist: kombu==5.5.3
Requires-Dist: lazy-model==0.2.0
Requires-Dist: line-bot-sdk==3.12.0
Requires-Dist: motor==3.7.1
Requires-Dist: multidict==6.4.3
Requires-Dist: prompt_toolkit==3.0.51
Requires-Dist: propcache==0.3.1
Requires-Dist: pydantic==2.11.3
Requires-Dist: pydantic-settings==2.9.1
Requires-Dist: pydantic_core==2.33.1
Requires-Dist: pymongo==4.13.0
Requires-Dist: python-dateutil==2.9.0.post0
Requires-Dist: python-dotenv==1.1.0
Requires-Dist: python-multipart==0.0.20
Requires-Dist: redis==6.1.0
Requires-Dist: requests==2.32.3
Requires-Dist: s3transfer==0.11.5
Requires-Dist: six==1.17.0
Requires-Dist: sniffio==1.3.1
Requires-Dist: starlette==0.46.1
Requires-Dist: toml==0.10.2
Requires-Dist: typing-inspection==0.4.0
Requires-Dist: typing_extensions==4.13.1
Requires-Dist: tzdata==2025.2
Requires-Dist: urllib3==2.3.0
Requires-Dist: uvicorn==0.34.0
Requires-Dist: vine==5.1.0
Requires-Dist: watchtower==3.4.0
Requires-Dist: wcwidth==0.2.13
Requires-Dist: wrapt==1.17.2
Requires-Dist: yarl==1.20.0
Dynamic: author
Dynamic: author-email
Dynamic: classifier
Dynamic: description
Dynamic: description-content-type
Dynamic: home-page
Dynamic: requires-dist
Dynamic: requires-python
Dynamic: summary
